requestor/__init__.py
requestor/api/main.py
requestor/cli/__init__.py
requestor/cli/commands.py
requestor/config.py
requestor/data/deployments/l2.json
requestor/db/__init__.py
requestor/db/sqlite.py
requestor/errors.py
requestor/payments/blockchain_service.py
requestor/payments/monitor.py
requestor/provider/__init__.py
requestor/provider/client.py
requestor/run.py
requestor/security/faucet.py
requestor/services/__init__.py
requestor/services/database_service.py
requestor/services/provider_service.py
requestor/services/ssh_service.py
requestor/services/vm_service.py
requestor/settings.py
requestor/ssh/__init__.py
requestor/ssh/manager.py
requestor/utils/logging.py
requestor/utils/spinner.py
request_vm_on_golem-0.1.58.dist-info/METADATA
request_vm_on_golem-0.1.58.dist-info/WHEEL
request_vm_on_golem-0.1.58.dist-info/entry_points.txt
request_vm_on_golem-0.1.58.dist-info/RECORD
