Metadata-Version: 2.3
Name: request-vm-on-golem
Version: 0.1.58
Summary: VM on Golem Requestor CLI - Create and manage virtual machines on the Golem Network
Keywords: golem,vm,cloud,decentralized,cli
Author: Phillip Jensen
Author-email: phillip+vm-on-golem@golemgrid.com
Requires-Python: >=3.11,<4.0
Classifier: Development Status :: 4 - Beta
Classifier: Environment :: Console
Classifier: Intended Audience :: Developers
Classifier: Intended Audience :: System Administrators
Classifier: Operating System :: OS Independent
Classifier: Programming Language :: Python :: 3
Classifier: Programming Language :: Python :: 3.11
Classifier: Programming Language :: Python :: 3.12
Classifier: Programming Language :: Python :: 3.13
Classifier: Topic :: System :: Distributed Computing
Classifier: Topic :: System :: Systems Administration
Requires-Dist: aiohttp (>=3.8.1,<4.0.0)
Requires-Dist: aiosqlite (>=0.17.0,<0.18.0)
Requires-Dist: asyncssh (>=2.7.0,<3.0.0)
Requires-Dist: click (>=8.0.1,<9.0.0)
Requires-Dist: colorlog (>=6.8.0,<7.0.0)
Requires-Dist: cryptography (>=3.4.7,<4.0.0)
Requires-Dist: fastapi (>=0.103.0,<0.104.0)
Requires-Dist: golem-base-sdk (==0.1.0)
Requires-Dist: golem-faucet (>=0.1.0,<0.2.0)
Requires-Dist: golem-streaming-abi (>=0.1.0,<0.2.0)
Requires-Dist: httptools (>=0.6.0,<0.7.0)
Requires-Dist: pydantic (>=2.4.0,<3.0.0)
Requires-Dist: pydantic-settings (>=2.1.0,<3.0.0)
Requires-Dist: python-dotenv (>=1.0.0,<2.0.0)
Requires-Dist: requests (>=2.31.0,<3.0.0)
Requires-Dist: tabulate (>=0.9.0,<0.10.0)
Requires-Dist: uvicorn[standard] (>=0.35.0,<0.36.0)
Requires-Dist: web3 (==7.13.0)
Project-URL: Homepage, https://github.com/cryptobench/vm-on-golem
Project-URL: Repository, https://github.com/cryptobench/vm-on-golem
